testbench_requirement_service/__init__.py
testbench_requirement_service/app.py
testbench_requirement_service/cli.py
testbench_requirement_service/middleware.py
testbench_requirement_service/openapi.yaml
testbench_requirement_service/routes.py
testbench_requirement_service/models/__init__.py
testbench_requirement_service/models/file_requirement.py
testbench_requirement_service/models/requirement.py
testbench_requirement_service/readers/ExcelFileReader.py
testbench_requirement_service/readers/FileReader.py
testbench_requirement_service/readers/JsonlFileReader.py
testbench_requirement_service/readers/__init__.py
testbench_requirement_service/readers/utils.py
testbench_requirement_service/utils/__init__.py
testbench_requirement_service/utils/auth.py
testbench_requirement_service/utils/date_format.py
testbench_requirement_service/utils/helpers.py
testbench_requirement_service-1.0.0a2.dist-info/entry_points.txt
testbench_requirement_service-1.0.0a2.dist-info/licenses/LICENSE
testbench_requirement_service-1.0.0a2.dist-info/WHEEL
testbench_requirement_service-1.0.0a2.dist-info/METADATA
testbench_requirement_service-1.0.0a2.dist-info/RECORD
