Metadata-Version: 2.4
Name: testbench-requirement-service
Version: 1.0.0a2
Summary: # TestBench Requirement Service
Author-email: René Rohner <rene.rohner@imbus.de>
Requires-Python: >=3.10
License-Expression: Apache-2.0
License-File: LICENSE
Requires-Dist: sanic>=24.12,<25.0
Requires-Dist: sanic-ext>=23.12,<25.0
Requires-Dist: pydantic>=2.10.6,<3.0.0
Requires-Dist: click>=8.1.8,<9.0.0
Requires-Dist: pandas>=2.2.3,<3.0.0
Requires-Dist: openpyxl>=3.1.5,<4.0.0
Requires-Dist: xlrd>=2.0.1,<3.0.0
Requires-Dist: javaproperties>=0.8.2,<1.0.0
Requires-Dist: ruff>=0.9.6 ; extra == "dev"
Requires-Dist: pre-commit>=4.1.0 ; extra == "dev"
Requires-Dist: invoke>=2.2.0 ; extra == "dev"
Requires-Dist: mypy>=1.15.0 ; extra == "dev"
Requires-Dist: flit>=3.10.1 ; extra == "dev"
Requires-Dist: wheel>=0.45.1 ; extra == "dev"
Requires-Dist: robotframework>=7.2.2 ; extra == "test"
Requires-Dist: robotframework-robocop>=5.8.1 ; extra == "test"
Requires-Dist: robotframework-tidy>=4.16.0 ; extra == "test"
Requires-Dist: requests>=2.32.3 ; extra == "test"
Project-URL: Home, https://github.com/imbus/testbench-requirement-service
Provides-Extra: dev
Provides-Extra: test
